README.md
setup.py
clitellum_evs.egg-info/PKG-INFO
clitellum_evs.egg-info/SOURCES.txt
clitellum_evs.egg-info/dependency_links.txt
clitellum_evs.egg-info/requires.txt
clitellum_evs.egg-info/top_level.txt
src/__init__.py
src/builder.py
src/entities.py
src/fsm.py
src/repository.py
src/snapshot.py
src/rejection/__init__.py
src/rejection/engines.py