Metadata-Version: 1.0
Name: clitellum-evs
Version: 1.2.5
Summary: Event Sourcing Library
Home-page: https://gitlab.com/clitellum/clitellum_evs/wikis/home
Author: Sergio.Bermudez
Author-email: sbermudezlozano@gmail.com
License: APACHE
Keywords: clitellum event sourcing eventsourcing
Platform: UNKNOWN
